README.md
setup.py
mmscrapy/__init__.py
mmscrapy/middlewares.py
mmscrapy/settings.py
mmscrapy.egg-info/PKG-INFO
mmscrapy.egg-info/SOURCES.txt
mmscrapy.egg-info/dependency_links.txt
mmscrapy.egg-info/entry_points.txt
mmscrapy.egg-info/top_level.txt
mmscrapy/items/ImageItem.py
mmscrapy/items/NovelItem.py
mmscrapy/items/__init__.py
mmscrapy/middleware/ProxyMiddleware.py
mmscrapy/middleware/RandomUserAgent.py
mmscrapy/middleware/__init__.py
mmscrapy/pipelines/ConsolePipeline.py
mmscrapy/pipelines/ImagePipeline.py
mmscrapy/pipelines/JsonFilePipeline.py
mmscrapy/pipelines/MongoPipeline.py
mmscrapy/pipelines/MysqlPipeline.py
mmscrapy/pipelines/__init__.py
mmscrapy/spiders/AuthorSpider.py
mmscrapy/spiders/CnvdLoopholeSpider.py
mmscrapy/spiders/FreeProxySpider.py
mmscrapy/spiders/FreebufLoopholeSpider.py
mmscrapy/spiders/ImageSpiders.py
mmscrapy/spiders/NovelSpiders.py
mmscrapy/spiders/QuotesSpider.py
mmscrapy/spiders/XiaohuarSpider.py
mmscrapy/spiders/__init__.py
mmscrapy/utils/SeleniumCookieUtil.py
mmscrapy/utils/SplashUtil.py
mmscrapy/utils/__init__.py